ingeniiadfg/__init__.py
ingeniiadfg/activities/__init__.py
ingeniiadfg/activities/data_lake.py
ingeniiadfg/activities/generic.py
ingeniiadfg/base.py
ingeniiadfg/defaults.py
ingeniiadfg/initialise.py
ingeniiadfg/main.py
ingeniiadfg/schedule.py
ingeniiadfg/sftp.py
ingeniiadfg/templates/__init__.py
ingeniiadfg/templates/dataset/__init__.py
ingeniiadfg/templates/dataset/config_table.py
ingeniiadfg/templates/dataset/data_lake.py
ingeniiadfg/templates/dataset/ftp.py
ingeniiadfg/templates/dataset/sftp.py
ingeniiadfg/templates/integration_runtime/self_hosted.py
ingeniiadfg/templates/linked_service/__init__.py
ingeniiadfg/templates/linked_service/config_table_storage.py
ingeniiadfg/templates/linked_service/credentials_store.py
ingeniiadfg/templates/linked_service/data_lake.py
ingeniiadfg/templates/linked_service/ftp.py
ingeniiadfg/templates/linked_service/sftp.py
ingeniiadfg/templates/trigger/schedule.py
ingeniiadfg-0.1.5.dist-info/entry_points.txt
ingeniiadfg-0.1.5.dist-info/WHEEL
ingeniiadfg-0.1.5.dist-info/METADATA
ingeniiadfg-0.1.5.dist-info/RECORD
