Metadata-Version: 2.1
Name: ingeniiadfg
Version: 0.1.5
Summary: Generate Azure Data Factory objects from configuration
Author: Greg Atkins
Author-email: greg@ingenii.dev
Requires-Python: >=3.9,<4.0
Classifier: Programming Language :: Python :: 3
Classifier: Programming Language :: Python :: 3.10
Classifier: Programming Language :: Python :: 3.9
Requires-Dist: deepdiff (==5.5.0)
Requires-Dist: typer[all] (>=0.4.0,<0.5.0)
